bulletinclient
